odoo8_addon_logistic_budget-8.0.2.3.1-py2.7-nspkg.pth
odoo_addons/logistic_budget/__openerp__.py
odoo_addons/logistic_budget/__init__.py
odoo_addons/logistic_budget/README.rst
odoo_addons/logistic_budget/view/sale_order.xml
odoo_addons/logistic_budget/view/report_logistic_requisition.xml
odoo_addons/logistic_budget/view/sale_order_budget_update.xml
odoo_addons/logistic_budget/view/logistic_requisition.xml
odoo_addons/logistic_budget/view/report_saleorder.xml
odoo_addons/logistic_budget/i18n/logistic_budget.pot
odoo_addons/logistic_budget/i18n/en_US.po
odoo_addons/logistic_budget/model/logistic_requisition.py
odoo_addons/logistic_budget/model/sale_order.py
odoo_addons/logistic_budget/model/source.py
odoo_addons/logistic_budget/model/__init__.py
odoo_addons/logistic_budget/wizard/cost_estimate.py
odoo_addons/logistic_budget/wizard/sale_order_budget_update.py
odoo_addons/logistic_budget/wizard/__init__.py
odoo_addons/logistic_budget/data/exceptions.xml
odoo_addons/logistic_budget/tests/test_propagate_budget.py
odoo_addons/logistic_budget/tests/__init__.py
odoo_addons/logistic_budget/tests/test_unit_check.py
odoo_addons/logistic_budget/tests/test_it_blocks.py
odoo8_addon_logistic_budget-8.0.2.3.1.dist-info/top_level.txt
odoo8_addon_logistic_budget-8.0.2.3.1.dist-info/WHEEL
odoo8_addon_logistic_budget-8.0.2.3.1.dist-info/RECORD
odoo8_addon_logistic_budget-8.0.2.3.1.dist-info/metadata.json
odoo8_addon_logistic_budget-8.0.2.3.1.dist-info/DESCRIPTION.rst
odoo8_addon_logistic_budget-8.0.2.3.1.dist-info/METADATA
odoo8_addon_logistic_budget-8.0.2.3.1.dist-info/namespace_packages.txt
